HACKING.rst
LICENSE
MANIFEST.in
README.rst
jingle.py
setup.py
bin/jingle
examples/broken.conf
examples/broken.j2
examples/circular.conf
examples/hello.conf
examples/hello.j2
examples/snow.conf
jingle.egg-info/PKG-INFO
jingle.egg-info/SOURCES.txt
jingle.egg-info/dependency_links.txt
jingle.egg-info/requires.txt
jingle.egg-info/top_level.txt
requirements/dev.txt
requirements/install.txt