Metadata-Version: 1.1
Name: jingle
Version: 0.2.1
Summary: Config files renderer based on Jinja2
Home-page: https://github.com/nimboost/jingle
Author: Kris Kovalik
Author-email: hi@kkvlk.me
License: MIT
Download-URL: https://github.com/nimboost/jingle/tarball/v0.2.1
Keywords: config file template jinja nimboost
Platform: UNKNOWN
Classifier: Development Status :: 3 - Alpha
Classifier: Topic :: Utilities
Classifier: Programming Language :: Python :: 2.5
Classifier: Programming Language :: Python :: 2.6
Classifier: Programming Language :: Python :: 2.7
Classifier: License :: OSI Approved :: MIT License
